planpy/__init__.py
planpy-0.0.8.dist-info/LICENSE
planpy-0.0.8.dist-info/METADATA
planpy-0.0.8.dist-info/WHEEL
planpy-0.0.8.dist-info/entry_points.txt
planpy-0.0.8.dist-info/top_level.txt
planpy-0.0.8.dist-info/RECORD
