Metadata-Version: 2.1
Name: planpy
Version: 0.0.8
Summary: An open source library for project management
Home-page: https://github.com/basanovase/planpy
Author: Flynn
Author-email: flynn.mclean@gmail.com
License: MIT
Platform: UNKNOWN
Classifier: License :: OSI Approved :: MIT License
Classifier: Programming Language :: Python :: 3
Classifier: Programming Language :: Python :: 3.8
Requires-Dist: dateutil
